MANIFEST.in
README.md
setup.py
pyramid_mako_clientscript/__init__.py
pyramid_mako_clientscript.egg-info/PKG-INFO
pyramid_mako_clientscript.egg-info/SOURCES.txt
pyramid_mako_clientscript.egg-info/dependency_links.txt
pyramid_mako_clientscript.egg-info/not-zip-safe
pyramid_mako_clientscript.egg-info/requires.txt
pyramid_mako_clientscript.egg-info/top_level.txt